docs/__init__.py
forex_python/__init__.py
forex_python/bitcoin.py
forex_python/converter.py
forex_python/raw_data/currencies.json
forex_python-1.9.1.dist-info/licenses/LICENSE
forex_python-1.9.1.dist-info/METADATA
forex_python-1.9.1.dist-info/WHEEL
forex_python-1.9.1.dist-info/top_level.txt
forex_python-1.9.1.dist-info/RECORD
