Metadata-Version: 2.4
Name: forex-python
Version: 1.9.1
Summary: Free foreign exchange rates and currency conversion.
Home-page: https://github.com/MicroPyramid/forex-python
Author: Micro Pyramid Informatic Pvt. Ltd.
Author-email: hello@micropyramid.com
Project-URL: Documentation, https://forex-python.readthedocs.io/
Project-URL: Source, https://github.com/MicroPyramid/forex-python
Project-URL: Tracker, https://github.com/MicroPyramid/forex-python/issues
Classifier: Intended Audience :: Developers
Classifier: Topic :: Software Development :: Internationalization
Classifier: License :: OSI Approved :: MIT License
Classifier: Operating System :: OS Independent
Classifier: Programming Language :: Python
Classifier: Programming Language :: Python :: 2.7
Classifier: Programming Language :: Python :: 3
Classifier: Programming Language :: Python :: 3.6
Classifier: Programming Language :: Python :: 3.7
Classifier: Programming Language :: Python :: 3.8
Classifier: Programming Language :: Python :: 3.9
Classifier: Programming Language :: Python :: 3.10
Requires-Python: >=2.7, !=3.0.*, !=3.1.*, !=3.2.*, <4
License-File: LICENSE
Requires-Dist: requests>=2.0
Requires-Dist: simplejson>=3.0
Dynamic: author
Dynamic: author-email
Dynamic: classifier
Dynamic: description
Dynamic: description-content-type
Dynamic: home-page
Dynamic: license-file
Dynamic: project-url
Dynamic: requires-dist
Dynamic: requires-python
Dynamic: summary
